{
  "_class": "page",
  "do_objectID": "79D878A4-8912-4FE2-ACCD-9FE72E6884F7",
  "exportOptions": {
    "_class": "exportOptions",
    "exportFormats": [
    ],
    "includedLayerIds": [
    ],
    "layerOptions": 0,
    "shouldTrim": false
  },
  "frame": {
    "_class": "rect",
    "constrainProportions": false,
    "height": 300,
    "width": 300,
    "x": 0,
    "y": 0
  },
  "hasClickThrough": true,
  "horizontalRulerData": {
    "_class": "rulerData",
    "base": 0,
    "guides": [
    ]
  },
  "includeInCloudUpload": true,
  "isFlippedHorizontal": false,
  "isFlippedVertical": false,
  "isLocked": false,
  "isVisible": true,
  "layerListExpandedType": 0,
  "layers": [
    {
      "class": "artboard",
      "id": "221A5EF6-50CD-4514-A975-8939B2BC6386"
    },
    {
      "class": "artboard",
      "id": "D01C5A8B-C593-4426-8115-03F3D3AFF497"
    }
  ],
  "name": "Miranda",
  "nameIsFixed": true,
  "resizingConstraint": 63,
  "resizingType": 0,
  "rotation": 0,
  "shouldBreakMaskChain": false,
  "style": {
    "_class": "style",
    "endDecorationType": 0,
    "miterLimit": 10,
    "startDecorationType": 0
  },
  "verticalRulerData": {
    "_class": "rulerData",
    "base": 0,
    "guides": [
    ]
  }
}